c66/__init__.py
c66-0.1.4.dist-info/METADATA
c66-0.1.4.dist-info/WHEEL
c66-0.1.4.dist-info/licenses/LICENSE
c66-0.1.4.dist-info/RECORD
