Metadata-Version: 2.4
Name: c66
Version: 0.1.4
Summary: A collection of handy Python utilities
Author-email: ChoCho66 <porkdie@gmail.com>
License-File: LICENSE
Requires-Python: >=3.7
